sitecats/__init__.py
sitecats/admin.py
sitecats/apps.py
sitecats/exceptions.py
sitecats/models.py
sitecats/settings.py
sitecats/toolbox.py
sitecats/utils.py
sitecats/locale/en/LC_MESSAGES/django.po
sitecats/locale/es/LC_MESSAGES/django.mo
sitecats/locale/es/LC_MESSAGES/django.po
sitecats/locale/ru/LC_MESSAGES/django.mo
sitecats/locale/ru/LC_MESSAGES/django.po
sitecats/migrations/0001_initial.py
sitecats/migrations/__init__.py
sitecats/static/js/sitecats/sitecats.js
sitecats/static/js/sitecats/sitecats.min.js
sitecats/templates/sitecats/categories.html
sitecats/templates/sitecats/choice_box.html
sitecats/templates/sitecats/list.html
sitecats/templates/sitecats/list_box.html
sitecats/templatetags/__init__.py
sitecats/templatetags/sitecats.py
sitecats/tests/__init__.py
sitecats/tests/conftest.py
sitecats/tests/test_basic.py
sitecats/tests/testapp/__init__.py
sitecats/tests/testapp/models.py
django_sitecats-1.2.2.dist-info/AUTHORS
django_sitecats-1.2.2.dist-info/LICENSE
django_sitecats-1.2.2.dist-info/METADATA
django_sitecats-1.2.2.dist-info/WHEEL
django_sitecats-1.2.2.dist-info/top_level.txt
django_sitecats-1.2.2.dist-info/RECORD
